puchipuchi_filler/__init__.py
puchipuchi_filler/abanlin.filler
puchipuchi_filler/angavrel.filler
puchipuchi_filler/carli.filler
puchipuchi_filler/champely.filler
puchipuchi_filler/grati.filler
puchipuchi_filler/hcao.filler
puchipuchi_filler/lcharvol.filler
puchipuchi_filler/main.py
puchipuchi_filler/main__.py
puchipuchi_filler/superjeannot.filler
puchipuchi_filler/thechef_filler.py
puchipuchi_filler-0.1.44.dist-info/entry_points.txt
puchipuchi_filler-0.1.44.dist-info/WHEEL
puchipuchi_filler-0.1.44.dist-info/METADATA
puchipuchi_filler-0.1.44.dist-info/RECORD
