Metadata-Version: 2.1
Name: puchipuchi-filler
Version: 0.1.44
Summary: no description provided
Author: puchipuchi team
Requires-Python: >=3.8
Classifier: Programming Language :: Python :: 3
Classifier: Programming Language :: Python :: 3.8
Classifier: Programming Language :: Python :: 3.9
